src/__init__.py
src/main.py
saman_py-0.1.1.dist-info/METADATA
saman_py-0.1.1.dist-info/WHEEL
saman_py-0.1.1.dist-info/RECORD
